[
  {
    "name": "Have you seen our new website?",
    "value":  "Have you seen our <a href='http://jampp.com' style='font-weight:bold; text-decoration:underline;'>new website</a>?"
  },
  {
    "name": "We are hiring geeks!",
    "value":  "<a href='http://jampp.com/jobs' style='font-weight:bold; text-decoration:underline;'>We are hiring</a> geeks!"
  },
  {
    "name": "Boosting mobile sales",
    "value":  "<a href='http://jampp.com' style='font-weight:bold'>Boost your mobile sales</a>"
  },
  {
    "name": "Check out our latest tech blog post",
    "value":  "<a href='http://geeks.jampp.com' style='font-weight:bold'>Check out our latest tech blog post</a>"
  },
  {
    "name": "Climbed Everest? Wrestled alligators? Next?? We're hiring!",
    "value":  "<a href='http://jampp.com/jobs' style='font-weight:bold'>Climbed Everest? Wrestled alligators? Next?? We're hiring!</a>"
  }
]